Metadata-Version: 2.1
Name: Adafruit-CCS811
Version: 0.2.1
Summary: Python library to use the CCS811 air quality sensor with raspberry pi or other linux boards.
Home-page: https://github.com/adafruit/Adafruit_CCS811_python/
Author: Dean Miller
Author-email: dean@adafruit.com
License: MIT
Platform: UNKNOWN
Classifier: Development Status :: 4 - Beta
Classifier: Operating System :: POSIX :: Linux
Classifier: License :: OSI Approved :: MIT License
Classifier: Intended Audience :: Developers
Classifier: Programming Language :: Python :: 2.7
Classifier: Programming Language :: Python :: 3
Classifier: Topic :: Software Development
Classifier: Topic :: System :: Hardware
